sampex/__init__.py
sampex/__main__.py
sampex/download.py
sampex/load.py
sampex/plot_sampex.py
sampex/tests/test_attitude.py
sampex/tests/test_downloader.py
sampex/tests/test_hilt.py
sampex/tests/test_lica.py
sampex/tests/test_pet.py
sampex-1.1.1.dist-info/licenses/LICENSE
sampex-1.1.1.dist-info/METADATA
sampex-1.1.1.dist-info/WHEEL
sampex-1.1.1.dist-info/entry_points.txt
sampex-1.1.1.dist-info/top_level.txt
sampex-1.1.1.dist-info/RECORD
