Metadata-Version: 2.4
Name: sampex
Version: 1.1.1
Summary: Programs to load and plot the SAMPEX satellite data.
Author-email: Mike Shumko <msshumko@gmail.com>
License-Expression: MIT
Project-URL: Documentation, https://sampex.readthedocs.io/en/latest/
Project-URL: Repository, https://github.com/mshumko/sampex
Project-URL: Issues, https://github.com/mshumko/sampex/issues
Keywords: data science,SAMPEX,satellite,HILT,PET,LICA
Classifier: Programming Language :: Python :: 3
Classifier: Programming Language :: Python :: 3.10
Classifier: Programming Language :: Python :: 3.11
Classifier: Programming Language :: Python :: 3.12
Classifier: Programming Language :: Python :: 3.13
Requires-Python: >=3.9
License-File: LICENSE
Requires-Dist: matplotlib
Requires-Dist: numpy
Requires-Dist: pandas>2.0.0
Requires-Dist: beautifulsoup4
Requires-Dist: requests
Provides-Extra: dev
Requires-Dist: bump2version; extra == "dev"
Requires-Dist: black; extra == "dev"
Requires-Dist: pytest; extra == "dev"
Requires-Dist: sphinx-copybutton; extra == "dev"
Requires-Dist: furo; extra == "dev"
Requires-Dist: nbsphinx; extra == "dev"
Dynamic: license-file
